setup.py
MapSpatBroadcaster/J2735Helper.py
MapSpatBroadcaster/MmitssSpat.py
MapSpatBroadcaster/Ntcip1202v2Blob.py
MapSpatBroadcaster/Phase.py
MapSpatBroadcaster/Spat.py
MapSpatBroadcaster/__init__.py
MapSpatBroadcaster/map-spat-broadcaster.py
MapSpatBroadcaster.egg-info/PKG-INFO
MapSpatBroadcaster.egg-info/SOURCES.txt
MapSpatBroadcaster.egg-info/dependency_links.txt
MapSpatBroadcaster.egg-info/top_level.txt