Metadata-Version: 2.1
Name: MapSpatBroadcaster
Version: 1.0
Summary: MAP-SPaT broadcaster classes and methods for MMITSS MRP
Author: Samuel Cornejo
Author-email: samuelcornejo@arizona.edu
Classifier: Programming Language :: Python :: 3
Classifier: License :: OSI Approved :: MIT License
Classifier: Operating System :: OS Independent
Requires-Python: >=3.6
